{
  "liver_id": "lee-roha",
  "video_start_timestamp": 1718794798,
  "video_url": "https://youtu.be/iBVUtsyemJs",
  "gta_day": 5,
  "probe": [
    {
      "t": 1718795032.0,
      "x": 2567,
      "y": 5816,
      "vt": 300.0
    },
    {
      "t": 1718795037.0,
      "x": 2617,
      "y": 5814,
      "vt": 305.0
    },
    {
      "t": 1718795042.0,
      "x": 2572,
      "y": 5809,
      "vt": 310.0
    },
    {
      "t": 1718795047.0,
      "x": 2578,
      "y": 5815,
      "vt": 315.0
    },
    {
      "t": 1718795052.0,
      "x": 2585,
      "y": 5812,
      "vt": 320.0
    },
    {
      "t": 1718795057.0,
      "x": 2574,
      "y": 5792,
      "vt": 325.0
    },
    {
      "t": 1718796657.0,
      "x": 2586,
      "y": 5820,
      "vt": 1925.0
    },
    {
      "t": 1718796667.0,
      "x": 2574,
      "y": 5839,
      "vt": 1935.0
    },
    {
      "t": 1718796672.0,
      "x": 2595,
      "y": 5851,
      "vt": 1940.0
    },
    {
      "t": 1718796687.0,
      "x": 2563,
      "y": 5837,
      "vt": 1955.0
    },
    {
      "t": 1718796692.0,
      "x": 2600,
      "y": 5834,
      "vt": 1960.0
    },
    {
      "t": 1718796737.0,
      "x": 2569,
      "y": 5830,
      "vt": 2005.0
    },
    {
      "t": 1718796742.0,
      "x": 2569,
      "y": 5832,
      "vt": 2010.0
    },
    {
      "t": 1718796747.0,
      "x": 2580,
      "y": 5832,
      "vt": 2015.0
    },
    {
      "t": 1718796752.0,
      "x": 2581,
      "y": 5837,
      "vt": 2020.0
    },
    {
      "t": 1718796757.0,
      "x": 2530,
      "y": 5839,
      "vt": 2025.0
    },
    {
      "t": 1718796767.0,
      "x": 2551,
      "y": 5741,
      "vt": 2035.0
    },
    {
      "t": 1718796977.0,
      "x": 1110,
      "y": 3351,
      "vt": 2245.0
    },
    {
      "t": 1718797097.0,
      "x": 2689,
      "y": 1515,
      "vt": 2365.0
    },
    {
      "t": 1718797102.0,
      "x": 2795,
      "y": 1393,
      "vt": 2370.0
    },
    {
      "t": 1718797107.0,
      "x": 2857,
      "y": 1319,
      "vt": 2375.0
    },
    {
      "t": 1718797492.0,
      "x": 2852,
      "y": 1331,
      "vt": 2760.0
    },
    {
      "t": 1718797502.0,
      "x": 2902,
      "y": 1295,
      "vt": 2770.0
    },
    {
      "t": 1718797512.0,
      "x": 2955,
      "y": 1265,
      "vt": 2780.0
    },
    {
      "t": 1718797517.0,
      "x": 2957,
      "y": 1267,
      "vt": 2785.0
    },
    {
      "t": 1718797522.0,
      "x": 2961,
      "y": 1255,
      "vt": 2790.0
    },
    {
      "t": 1718797527.0,
      "x": 2960,
      "y": 1265,
      "vt": 2795.0
    },
    {
      "t": 1718797532.0,
      "x": 2951,
      "y": 1265,
      "vt": 2800.0
    },
    {
      "t": 1718797537.0,
      "x": 2967,
      "y": 1258,
      "vt": 2805.0
    },
    {
      "t": 1718797542.0,
      "x": 3017,
      "y": 1261,
      "vt": 2810.0
    },
    {
      "t": 1718797552.0,
      "x": 3266,
      "y": 1271,
      "vt": 2820.0
    },
    {
      "t": 1718797612.0,
      "x": 4617,
      "y": 2198,
      "vt": 2880.0
    },
    {
      "t": 1718797622.0,
      "x": 4680,
      "y": 2485,
      "vt": 2890.0
    },
    {
      "t": 1718797627.0,
      "x": 4711,
      "y": 2643,
      "vt": 2895.0
    },
    {
      "t": 1718797687.0,
      "x": 4509,
      "y": 3782,
      "vt": 2955.0
    },
    {
      "t": 1718797692.0,
      "x": 4541,
      "y": 3822,
      "vt": 2960.0
    },
    {
      "t": 1718797697.0,
      "x": 4564,
      "y": 3871,
      "vt": 2965.0
    },
    {
      "t": 1718797707.0,
      "x": 4614,
      "y": 3865,
      "vt": 2975.0
    },
    {
      "t": 1718797757.0,
      "x": 4832,
      "y": 3794,
      "vt": 3025.0
    },
    {
      "t": 1718797767.0,
      "x": 4786,
      "y": 3860,
      "vt": 3035.0
    },
    {
      "t": 1718798202.0,
      "x": 4859,
      "y": 3851,
      "vt": 3470.0
    },
    {
      "t": 1718798212.0,
      "x": 4851,
      "y": 3856,
      "vt": 3480.0
    },
    {
      "t": 1718798227.0,
      "x": 4870,
      "y": 3841,
      "vt": 3495.0
    },
    {
      "t": 1718798232.0,
      "x": 4849,
      "y": 3795,
      "vt": 3500.0
    },
    {
      "t": 1718798237.0,
      "x": 4790,
      "y": 3800,
      "vt": 3505.0
    },
    {
      "t": 1718798247.0,
      "x": 4714,
      "y": 3845,
      "vt": 3515.0
    },
    {
      "t": 1718798252.0,
      "x": 4668,
      "y": 3874,
      "vt": 3520.0
    },
    {
      "t": 1718798257.0,
      "x": 4558,
      "y": 3878,
      "vt": 3525.0
    },
    {
      "t": 1718798262.0,
      "x": 4589,
      "y": 3942,
      "vt": 3530.0
    },
    {
      "t": 1718798287.0,
      "x": 4566,
      "y": 4618,
      "vt": 3555.0
    },
    {
      "t": 1718798292.0,
      "x": 4565,
      "y": 4621,
      "vt": 3560.0
    },
    {
      "t": 1718798307.0,
      "x": 4503,
      "y": 4857,
      "vt": 3575.0
    },
    {
      "t": 1718798327.0,
      "x": 4345,
      "y": 4909,
      "vt": 3595.0
    },
    {
      "t": 1718798367.0,
      "x": 4420,
      "y": 6022,
      "vt": 3635.0
    },
    {
      "t": 1718798402.0,
      "x": 3532,
      "y": 6633,
      "vt": 3670.0
    },
    {
      "t": 1718798407.0,
      "x": 3543,
      "y": 6785,
      "vt": 3675.0
    },
    {
      "t": 1718798412.0,
      "x": 3553,
      "y": 6907,
      "vt": 3680.0
    },
    {
      "t": 1718798417.0,
      "x": 3584,
      "y": 7000,
      "vt": 3685.0
    },
    {
      "t": 1718798427.0,
      "x": 3550,
      "y": 7054,
      "vt": 3695.0
    },
    {
      "t": 1718798432.0,
      "x": 3557,
      "y": 7073,
      "vt": 3700.0
    },
    {
      "t": 1718798437.0,
      "x": 3558,
      "y": 7073,
      "vt": 3705.0
    },
    {
      "t": 1718798582.0,
      "x": 3553,
      "y": 7079,
      "vt": 3850.0
    },
    {
      "t": 1718798587.0,
      "x": 3600,
      "y": 7065,
      "vt": 3855.0
    },
    {
      "t": 1718798592.0,
      "x": 3559,
      "y": 7069,
      "vt": 3860.0
    },
    {
      "t": 1718798597.0,
      "x": 3556,
      "y": 7079,
      "vt": 3865.0
    },
    {
      "t": 1718798602.0,
      "x": 3556,
      "y": 7073,
      "vt": 3870.0
    },
    {
      "t": 1718798607.0,
      "x": 3548,
      "y": 7077,
      "vt": 3875.0
    },
    {
      "t": 1718798612.0,
      "x": 3550,
      "y": 7070,
      "vt": 3880.0
    },
    {
      "t": 1718798617.0,
      "x": 3545,
      "y": 7029,
      "vt": 3885.0
    },
    {
      "t": 1718798622.0,
      "x": 3571,
      "y": 7016,
      "vt": 3890.0
    },
    {
      "t": 1718798627.0,
      "x": 3615,
      "y": 6985,
      "vt": 3895.0
    },
    {
      "t": 1718798637.0,
      "x": 3563,
      "y": 6792,
      "vt": 3905.0
    },
    {
      "t": 1718798642.0,
      "x": 3548,
      "y": 6648,
      "vt": 3910.0
    },
    {
      "t": 1718798647.0,
      "x": 3536,
      "y": 6476,
      "vt": 3915.0
    },
    {
      "t": 1718798652.0,
      "x": 3515,
      "y": 6349,
      "vt": 3920.0
    },
    {
      "t": 1718798657.0,
      "x": 3436,
      "y": 6227,
      "vt": 3925.0
    },
    {
      "t": 1718798662.0,
      "x": 3344,
      "y": 6170,
      "vt": 3930.0
    },
    {
      "t": 1718798672.0,
      "x": 3114,
      "y": 6074,
      "vt": 3940.0
    },
    {
      "t": 1718798682.0,
      "x": 3154,
      "y": 6082,
      "vt": 3950.0
    },
    {
      "t": 1718798692.0,
      "x": 3030,
      "y": 6030,
      "vt": 3960.0
    },
    {
      "t": 1718798697.0,
      "x": 2943,
      "y": 5972,
      "vt": 3965.0
    },
    {
      "t": 1718798702.0,
      "x": 2802,
      "y": 5909,
      "vt": 3970.0
    },
    {
      "t": 1718798707.0,
      "x": 2643,
      "y": 5837,
      "vt": 3975.0
    },
    {
      "t": 1718798907.0,
      "x": 2532,
      "y": 5823,
      "vt": 4175.0
    },
    {
      "t": 1718799177.0,
      "x": 2558,
      "y": 5823,
      "vt": 4445.0
    },
    {
      "t": 1718799187.0,
      "x": 2540,
      "y": 5839,
      "vt": 4455.0
    },
    {
      "t": 1718799197.0,
      "x": 2553,
      "y": 5803,
      "vt": 4465.0
    },
    {
      "t": 1718799202.0,
      "x": 2555,
      "y": 5808,
      "vt": 4470.0
    },
    {
      "t": 1718799207.0,
      "x": 2580,
      "y": 5839,
      "vt": 4475.0
    },
    {
      "t": 1718799212.0,
      "x": 2592,
      "y": 5865,
      "vt": 4480.0
    },
    {
      "t": 1718799217.0,
      "x": 2599,
      "y": 5851,
      "vt": 4485.0
    },
    {
      "t": 1718799222.0,
      "x": 2610,
      "y": 5855,
      "vt": 4490.0
    },
    {
      "t": 1718799227.0,
      "x": 2644,
      "y": 5852,
      "vt": 4495.0
    },
    {
      "t": 1718799232.0,
      "x": 2680,
      "y": 5855,
      "vt": 4500.0
    },
    {
      "t": 1718799237.0,
      "x": 2687,
      "y": 5854,
      "vt": 4505.0
    },
    {
      "t": 1718799242.0,
      "x": 2693,
      "y": 5867,
      "vt": 4510.0
    },
    {
      "t": 1718805477.0,
      "x": 2585,
      "y": 5835,
      "vt": 10745.0
    },
    {
      "t": 1718805572.0,
      "x": 2600,
      "y": 6316,
      "vt": 10840.0
    },
    {
      "t": 1718805587.0,
      "x": 2450,
      "y": 6389,
      "vt": 10855.0
    },
    {
      "t": 1718805592.0,
      "x": 2403,
      "y": 6392,
      "vt": 10860.0
    },
    {
      "t": 1718805802.0,
      "x": 2349,
      "y": 6420,
      "vt": 11070.0
    },
    {
      "t": 1718805877.0,
      "x": 2663,
      "y": 6187,
      "vt": 11145.0
    },
    {
      "t": 1718805897.0,
      "x": 2729,
      "y": 5859,
      "vt": 11165.0
    },
    {
      "t": 1718805902.0,
      "x": 2699,
      "y": 5864,
      "vt": 11170.0
    },
    {
      "t": 1718805907.0,
      "x": 2690,
      "y": 5848,
      "vt": 11175.0
    },
    {
      "t": 1718805912.0,
      "x": 2714,
      "y": 5850,
      "vt": 11180.0
    },
    {
      "t": 1718805917.0,
      "x": 2704,
      "y": 5841,
      "vt": 11185.0
    },
    {
      "t": 1718805922.0,
      "x": 2657,
      "y": 5855,
      "vt": 11190.0
    },
    {
      "t": 1718806357.0,
      "x": 2672,
      "y": 5886,
      "vt": 11625.0
    },
    {
      "t": 1718806362.0,
      "x": 2696,
      "y": 5894,
      "vt": 11630.0
    },
    {
      "t": 1718806377.0,
      "x": 2700,
      "y": 5859,
      "vt": 11645.0
    },
    {
      "t": 1718806382.0,
      "x": 2697,
      "y": 5860,
      "vt": 11650.0
    },
    {
      "t": 1718806407.0,
      "x": 2701,
      "y": 5827,
      "vt": 11675.0
    },
    {
      "t": 1718806412.0,
      "x": 2694,
      "y": 5862,
      "vt": 11680.0
    },
    {
      "t": 1718806417.0,
      "x": 2699,
      "y": 5857,
      "vt": 11685.0
    },
    {
      "t": 1718806422.0,
      "x": 2696,
      "y": 5857,
      "vt": 11690.0
    },
    {
      "t": 1718806427.0,
      "x": 2698,
      "y": 5858,
      "vt": 11695.0
    },
    {
      "t": 1718806472.0,
      "x": 2726,
      "y": 5875,
      "vt": 11740.0
    },
    {
      "t": 1718806477.0,
      "x": 2731,
      "y": 5870,
      "vt": 11745.0
    },
    {
      "t": 1718806537.0,
      "x": 2712,
      "y": 5889,
      "vt": 11805.0
    },
    {
      "t": 1718806542.0,
      "x": 2714,
      "y": 5891,
      "vt": 11810.0
    },
    {
      "t": 1718806547.0,
      "x": 2719,
      "y": 5874,
      "vt": 11815.0
    },
    {
      "t": 1718806552.0,
      "x": 2713,
      "y": 5876,
      "vt": 11820.0
    },
    {
      "t": 1718806557.0,
      "x": 2693,
      "y": 5893,
      "vt": 11825.0
    },
    {
      "t": 1718806562.0,
      "x": 2691,
      "y": 5892,
      "vt": 11830.0
    },
    {
      "t": 1718806567.0,
      "x": 2687,
      "y": 5893,
      "vt": 11835.0
    },
    {
      "t": 1718806572.0,
      "x": 2694,
      "y": 5832,
      "vt": 11840.0
    },
    {
      "t": 1718806577.0,
      "x": 2711,
      "y": 5834,
      "vt": 11845.0
    },
    {
      "t": 1718806587.0,
      "x": 2653,
      "y": 5850,
      "vt": 11855.0
    },
    {
      "t": 1718806592.0,
      "x": 2551,
      "y": 5813,
      "vt": 11860.0
    },
    {
      "t": 1718806597.0,
      "x": 2574,
      "y": 5853,
      "vt": 11865.0
    },
    {
      "t": 1718806602.0,
      "x": 2584,
      "y": 5860,
      "vt": 11870.0
    },
    {
      "t": 1718806607.0,
      "x": 2628,
      "y": 5836,
      "vt": 11875.0
    },
    {
      "t": 1718806622.0,
      "x": 2652,
      "y": 5788,
      "vt": 11890.0
    },
    {
      "t": 1718806632.0,
      "x": 2642,
      "y": 5782,
      "vt": 11900.0
    },
    {
      "t": 1718806652.0,
      "x": 2397,
      "y": 6002,
      "vt": 11920.0
    },
    {
      "t": 1718806657.0,
      "x": 2392,
      "y": 6110,
      "vt": 11925.0
    },
    {
      "t": 1718806662.0,
      "x": 2391,
      "y": 6230,
      "vt": 11930.0
    },
    {
      "t": 1718806667.0,
      "x": 2390,
      "y": 6334,
      "vt": 11935.0
    },
    {
      "t": 1718806672.0,
      "x": 2375,
      "y": 6381,
      "vt": 11940.0
    },
    {
      "t": 1718806677.0,
      "x": 2336,
      "y": 6377,
      "vt": 11945.0
    },
    {
      "t": 1718806682.0,
      "x": 2332,
      "y": 6373,
      "vt": 11950.0
    },
    {
      "t": 1718806687.0,
      "x": 2333,
      "y": 6372,
      "vt": 11955.0
    },
    {
      "t": 1718806692.0,
      "x": 2335,
      "y": 6372,
      "vt": 11960.0
    },
    {
      "t": 1718807007.0,
      "x": 2332,
      "y": 6382,
      "vt": 12275.0
    },
    {
      "t": 1718807012.0,
      "x": 2345,
      "y": 6382,
      "vt": 12280.0
    },
    {
      "t": 1718807022.0,
      "x": 2476,
      "y": 6356,
      "vt": 12290.0
    },
    {
      "t": 1718807027.0,
      "x": 2474,
      "y": 6261,
      "vt": 12295.0
    },
    {
      "t": 1718807032.0,
      "x": 2455,
      "y": 6194,
      "vt": 12300.0
    },
    {
      "t": 1718807037.0,
      "x": 2396,
      "y": 6179,
      "vt": 12305.0
    },
    {
      "t": 1718807042.0,
      "x": 2332,
      "y": 6182,
      "vt": 12310.0
    },
    {
      "t": 1718807047.0,
      "x": 2317,
      "y": 6159,
      "vt": 12315.0
    },
    {
      "t": 1718807052.0,
      "x": 2315,
      "y": 6149,
      "vt": 12320.0
    },
    {
      "t": 1718807057.0,
      "x": 2323,
      "y": 6125,
      "vt": 12325.0
    },
    {
      "t": 1718807062.0,
      "x": 2318,
      "y": 6162,
      "vt": 12330.0
    },
    {
      "t": 1718807067.0,
      "x": 2343,
      "y": 6181,
      "vt": 12335.0
    },
    {
      "t": 1718807072.0,
      "x": 2374,
      "y": 6175,
      "vt": 12340.0
    },
    {
      "t": 1718807092.0,
      "x": 2387,
      "y": 6055,
      "vt": 12360.0
    },
    {
      "t": 1718807097.0,
      "x": 2350,
      "y": 5988,
      "vt": 12365.0
    },
    {
      "t": 1718807127.0,
      "x": 2473,
      "y": 5926,
      "vt": 12395.0
    },
    {
      "t": 1718807132.0,
      "x": 2450,
      "y": 5855,
      "vt": 12400.0
    },
    {
      "t": 1718807137.0,
      "x": 2456,
      "y": 5846,
      "vt": 12405.0
    },
    {
      "t": 1718807142.0,
      "x": 2524,
      "y": 5819,
      "vt": 12410.0
    },
    {
      "t": 1718807152.0,
      "x": 2622,
      "y": 5806,
      "vt": 12420.0
    },
    {
      "t": 1718807167.0,
      "x": 2579,
      "y": 5814,
      "vt": 12435.0
    },
    {
      "t": 1718807752.0,
      "x": 2591,
      "y": 5854,
      "vt": 13020.0
    },
    {
      "t": 1718807807.0,
      "x": 2364,
      "y": 6009,
      "vt": 13075.0
    },
    {
      "t": 1718807812.0,
      "x": 2351,
      "y": 6110,
      "vt": 13080.0
    },
    {
      "t": 1718807817.0,
      "x": 2368,
      "y": 6224,
      "vt": 13085.0
    },
    {
      "t": 1718807822.0,
      "x": 2356,
      "y": 6288,
      "vt": 13090.0
    },
    {
      "t": 1718807827.0,
      "x": 2366,
      "y": 6395,
      "vt": 13095.0
    },
    {
      "t": 1718807832.0,
      "x": 2357,
      "y": 6393,
      "vt": 13100.0
    },
    {
      "t": 1718807837.0,
      "x": 2341,
      "y": 6425,
      "vt": 13105.0
    },
    {
      "t": 1718807842.0,
      "x": 2266,
      "y": 6474,
      "vt": 13110.0
    },
    {
      "t": 1718807847.0,
      "x": 2172,
      "y": 6525,
      "vt": 13115.0
    },
    {
      "t": 1718807852.0,
      "x": 2063,
      "y": 6609,
      "vt": 13120.0
    },
    {
      "t": 1718807857.0,
      "x": 2021,
      "y": 6652,
      "vt": 13125.0
    },
    {
      "t": 1718807862.0,
      "x": 2010,
      "y": 6683,
      "vt": 13130.0
    },
    {
      "t": 1718808537.0,
      "x": 2020,
      "y": 6671,
      "vt": 13805.0
    },
    {
      "t": 1718808547.0,
      "x": 2022,
      "y": 6672,
      "vt": 13815.0
    },
    {
      "t": 1718808627.0,
      "x": 2722,
      "y": 5869,
      "vt": 13895.0
    },
    {
      "t": 1718808632.0,
      "x": 2517,
      "y": 5819,
      "vt": 13900.0
    },
    {
      "t": 1718808637.0,
      "x": 2512,
      "y": 5808,
      "vt": 13905.0
    },
    {
      "t": 1718808662.0,
      "x": 2580,
      "y": 5865,
      "vt": 13930.0
    },
    {
      "t": 1718808712.0,
      "x": 2589,
      "y": 5870,
      "vt": 13980.0
    },
    {
      "t": 1718808732.0,
      "x": 2502,
      "y": 5795,
      "vt": 14000.0
    },
    {
      "t": 1718808797.0,
      "x": 2562,
      "y": 5862,
      "vt": 14065.0
    },
    {
      "t": 1718810232.0,
      "x": 2587,
      "y": 5045,
      "vt": 15500.0
    },
    {
      "t": 1718811572.0,
      "x": 2587,
      "y": 5045,
      "vt": 16840.0
    },
    {
      "t": 1718811862.0,
      "x": 2577,
      "y": 5821,
      "vt": 17130.0
    },
    {
      "t": 1718811867.0,
      "x": 2583,
      "y": 5843,
      "vt": 17135.0
    },
    {
      "t": 1718811912.0,
      "x": 2752,
      "y": 5940,
      "vt": 17180.0
    },
    {
      "t": 1718811917.0,
      "x": 2769,
      "y": 5905,
      "vt": 17185.0
    },
    {
      "t": 1718811922.0,
      "x": 2798,
      "y": 5896,
      "vt": 17190.0
    },
    {
      "t": 1718811932.0,
      "x": 2977,
      "y": 5977,
      "vt": 17200.0
    },
    {
      "t": 1718811937.0,
      "x": 3092,
      "y": 6009,
      "vt": 17205.0
    },
    {
      "t": 1718811997.0,
      "x": 3573,
      "y": 5845,
      "vt": 17265.0
    },
    {
      "t": 1718812022.0,
      "x": 3686,
      "y": 5881,
      "vt": 17290.0
    },
    {
      "t": 1718812047.0,
      "x": 3733,
      "y": 5830,
      "vt": 17315.0
    },
    {
      "t": 1718812072.0,
      "x": 4229,
      "y": 4890,
      "vt": 17340.0
    },
    {
      "t": 1718812077.0,
      "x": 4218,
      "y": 4858,
      "vt": 17345.0
    },
    {
      "t": 1718812232.0,
      "x": 4054,
      "y": 5524,
      "vt": 17500.0
    },
    {
      "t": 1718812237.0,
      "x": 4055,
      "y": 5504,
      "vt": 17505.0
    },
    {
      "t": 1718812247.0,
      "x": 4064,
      "y": 5458,
      "vt": 17515.0
    },
    {
      "t": 1718812467.0,
      "x": 2587,
      "y": 5045,
      "vt": 17735.0
    },
    {
      "t": 1718812472.0,
      "x": 2587,
      "y": 5045,
      "vt": 17740.0
    },
    {
      "t": 1718812517.0,
      "x": 4104,
      "y": 5422,
      "vt": 17785.0
    },
    {
      "t": 1718812532.0,
      "x": 4101,
      "y": 5442,
      "vt": 17800.0
    },
    {
      "t": 1718812537.0,
      "x": 4093,
      "y": 5442,
      "vt": 17805.0
    },
    {
      "t": 1718813322.0,
      "x": 3425,
      "y": 5836,
      "vt": 18590.0
    },
    {
      "t": 1718813327.0,
      "x": 3419,
      "y": 5821,
      "vt": 18595.0
    },
    {
      "t": 1718813342.0,
      "x": 3510,
      "y": 5869,
      "vt": 18610.0
    },
    {
      "t": 1718813347.0,
      "x": 3455,
      "y": 5862,
      "vt": 18615.0
    },
    {
      "t": 1718813352.0,
      "x": 3455,
      "y": 5897,
      "vt": 18620.0
    },
    {
      "t": 1718813357.0,
      "x": 3457,
      "y": 5901,
      "vt": 18625.0
    },
    {
      "t": 1718813362.0,
      "x": 3510,
      "y": 5904,
      "vt": 18630.0
    },
    {
      "t": 1718813367.0,
      "x": 3527,
      "y": 5940,
      "vt": 18635.0
    },
    {
      "t": 1718813372.0,
      "x": 3541,
      "y": 5961,
      "vt": 18640.0
    },
    {
      "t": 1718813377.0,
      "x": 3558,
      "y": 5970,
      "vt": 18645.0
    },
    {
      "t": 1718813382.0,
      "x": 3566,
      "y": 5975,
      "vt": 18650.0
    },
    {
      "t": 1718813387.0,
      "x": 3600,
      "y": 5960,
      "vt": 18655.0
    },
    {
      "t": 1718813392.0,
      "x": 3575,
      "y": 5981,
      "vt": 18660.0
    },
    {
      "t": 1718813397.0,
      "x": 3568,
      "y": 5981,
      "vt": 18665.0
    },
    {
      "t": 1718813402.0,
      "x": 3560,
      "y": 5993,
      "vt": 18670.0
    },
    {
      "t": 1718813427.0,
      "x": 2587,
      "y": 5045,
      "vt": 18695.0
    },
    {
      "t": 1718813437.0,
      "x": 2587,
      "y": 5045,
      "vt": 18705.0
    },
    {
      "t": 1718813507.0,
      "x": 2587,
      "y": 5031,
      "vt": 18775.0
    },
    {
      "t": 1718813547.0,
      "x": 2587,
      "y": 5045,
      "vt": 18815.0
    },
    {
      "t": 1718813577.0,
      "x": 2587,
      "y": 5045,
      "vt": 18845.0
    },
    {
      "t": 1718813607.0,
      "x": 2587,
      "y": 5045,
      "vt": 18875.0
    },
    {
      "t": 1718813637.0,
      "x": 2587,
      "y": 5045,
      "vt": 18905.0
    },
    {
      "t": 1718813682.0,
      "x": 2674,
      "y": 5852,
      "vt": 18950.0
    },
    {
      "t": 1718813722.0,
      "x": 2717,
      "y": 5792,
      "vt": 18990.0
    },
    {
      "t": 1718813727.0,
      "x": 2636,
      "y": 5804,
      "vt": 18995.0
    },
    {
      "t": 1718813732.0,
      "x": 2593,
      "y": 5865,
      "vt": 19000.0
    },
    {
      "t": 1718813737.0,
      "x": 2566,
      "y": 5875,
      "vt": 19005.0
    },
    {
      "t": 1718813747.0,
      "x": 2563,
      "y": 5834,
      "vt": 19015.0
    },
    {
      "t": 1718813772.0,
      "x": 2587,
      "y": 5045,
      "vt": 19040.0
    },
    {
      "t": 1718813777.0,
      "x": 2587,
      "y": 5045,
      "vt": 19045.0
    },
    {
      "t": 1718813787.0,
      "x": 2587,
      "y": 5045,
      "vt": 19055.0
    },
    {
      "t": 1718813792.0,
      "x": 2587,
      "y": 5045,
      "vt": 19060.0
    },
    {
      "t": 1718813962.0,
      "x": 2587,
      "y": 5045,
      "vt": 19230.0
    },
    {
      "t": 1718814367.0,
      "x": 2583,
      "y": 5839,
      "vt": 19635.0
    },
    {
      "t": 1718814382.0,
      "x": 2658,
      "y": 5847,
      "vt": 19650.0
    },
    {
      "t": 1718814387.0,
      "x": 2692,
      "y": 5855,
      "vt": 19655.0
    },
    {
      "t": 1718814412.0,
      "x": 3040,
      "y": 6051,
      "vt": 19680.0
    },
    {
      "t": 1718814427.0,
      "x": 2979,
      "y": 6224,
      "vt": 19695.0
    },
    {
      "t": 1718814437.0,
      "x": 2949,
      "y": 6284,
      "vt": 19705.0
    },
    {
      "t": 1718814442.0,
      "x": 2952,
      "y": 6261,
      "vt": 19710.0
    },
    {
      "t": 1718814447.0,
      "x": 2972,
      "y": 6202,
      "vt": 19715.0
    },
    {
      "t": 1718814452.0,
      "x": 3015,
      "y": 6136,
      "vt": 19720.0
    },
    {
      "t": 1718814457.0,
      "x": 3048,
      "y": 6141,
      "vt": 19725.0
    },
    {
      "t": 1718814612.0,
      "x": 3035,
      "y": 6192,
      "vt": 19880.0
    },
    {
      "t": 1718814617.0,
      "x": 3031,
      "y": 6189,
      "vt": 19885.0
    },
    {
      "t": 1718814622.0,
      "x": 3049,
      "y": 6203,
      "vt": 19890.0
    },
    {
      "t": 1718815197.0,
      "x": 3035,
      "y": 6023,
      "vt": 20465.0
    },
    {
      "t": 1718815202.0,
      "x": 2989,
      "y": 5982,
      "vt": 20470.0
    },
    {
      "t": 1718815207.0,
      "x": 2954,
      "y": 5974,
      "vt": 20475.0
    },
    {
      "t": 1718815212.0,
      "x": 2912,
      "y": 5957,
      "vt": 20480.0
    },
    {
      "t": 1718815217.0,
      "x": 2835,
      "y": 5913,
      "vt": 20485.0
    },
    {
      "t": 1718815222.0,
      "x": 2781,
      "y": 5895,
      "vt": 20490.0
    },
    {
      "t": 1718815227.0,
      "x": 2690,
      "y": 5863,
      "vt": 20495.0
    },
    {
      "t": 1718815232.0,
      "x": 2542,
      "y": 5884,
      "vt": 20500.0
    },
    {
      "t": 1718815237.0,
      "x": 2572,
      "y": 5869,
      "vt": 20505.0
    },
    {
      "t": 1718815242.0,
      "x": 2567,
      "y": 5836,
      "vt": 20510.0
    },
    {
      "t": 1718815247.0,
      "x": 2578,
      "y": 5830,
      "vt": 20515.0
    },
    {
      "t": 1718815832.0,
      "x": 2672,
      "y": 6334,
      "vt": 21100.0
    },
    {
      "t": 1718815837.0,
      "x": 2677,
      "y": 6416,
      "vt": 21105.0
    },
    {
      "t": 1718815842.0,
      "x": 2647,
      "y": 6555,
      "vt": 21110.0
    },
    {
      "t": 1718815847.0,
      "x": 2649,
      "y": 6699,
      "vt": 21115.0
    },
    {
      "t": 1718815852.0,
      "x": 2729,
      "y": 6757,
      "vt": 21120.0
    },
    {
      "t": 1718815862.0,
      "x": 2716,
      "y": 6904,
      "vt": 21130.0
    },
    {
      "t": 1718815867.0,
      "x": 2721,
      "y": 6907,
      "vt": 21135.0
    },
    {
      "t": 1718815872.0,
      "x": 2546,
      "y": 7164,
      "vt": 21140.0
    },
    {
      "t": 1718815882.0,
      "x": 2514,
      "y": 7099,
      "vt": 21150.0
    },
    {
      "t": 1718815887.0,
      "x": 2690,
      "y": 7050,
      "vt": 21155.0
    },
    {
      "t": 1718815892.0,
      "x": 2720,
      "y": 7104,
      "vt": 21160.0
    },
    {
      "t": 1718815897.0,
      "x": 2708,
      "y": 7103,
      "vt": 21165.0
    },
    {
      "t": 1718815902.0,
      "x": 2710,
      "y": 7116,
      "vt": 21170.0
    },
    {
      "t": 1718815907.0,
      "x": 2648,
      "y": 7154,
      "vt": 21175.0
    },
    {
      "t": 1718815912.0,
      "x": 2658,
      "y": 7160,
      "vt": 21180.0
    },
    {
      "t": 1718815927.0,
      "x": 2623,
      "y": 7143,
      "vt": 21195.0
    },
    {
      "t": 1718815932.0,
      "x": 2632,
      "y": 7134,
      "vt": 21200.0
    },
    {
      "t": 1718816587.0,
      "x": 2648,
      "y": 7164,
      "vt": 21855.0
    },
    {
      "t": 1718816612.0,
      "x": 2538,
      "y": 7008,
      "vt": 21880.0
    },
    {
      "t": 1718816632.0,
      "x": 2685,
      "y": 7027,
      "vt": 21900.0
    },
    {
      "t": 1718816642.0,
      "x": 2599,
      "y": 6922,
      "vt": 21910.0
    },
    {
      "t": 1718816652.0,
      "x": 2669,
      "y": 6687,
      "vt": 21920.0
    },
    {
      "t": 1718816657.0,
      "x": 3050,
      "y": 6405,
      "vt": 21925.0
    },
    {
      "t": 1718816662.0,
      "x": 2676,
      "y": 6475,
      "vt": 21930.0
    },
    {
      "t": 1718816667.0,
      "x": 2703,
      "y": 6413,
      "vt": 21935.0
    },
    {
      "t": 1718816677.0,
      "x": 2632,
      "y": 6306,
      "vt": 21945.0
    },
    {
      "t": 1718816687.0,
      "x": 2695,
      "y": 6236,
      "vt": 21955.0
    },
    {
      "t": 1718816692.0,
      "x": 2704,
      "y": 6135,
      "vt": 21960.0
    },
    {
      "t": 1718816717.0,
      "x": 2574,
      "y": 5857,
      "vt": 21985.0
    },
    {
      "t": 1718817792.0,
      "x": 2563,
      "y": 5828,
      "vt": 23060.0
    },
    {
      "t": 1718817797.0,
      "x": 2555,
      "y": 5816,
      "vt": 23065.0
    },
    {
      "t": 1718818777.0,
      "x": 1530,
      "y": 6029,
      "vt": 24045.0
    }
  ]
}